fastfood/__about__.py
fastfood/__init__.py
fastfood/book.py
fastfood/exc.py
fastfood/food.py
fastfood/pack.py
fastfood/shell.py
fastfood/stencil.py
fastfood/templating.py
fastfood/utils.py
fastfood-1.1.0.dist-info/DESCRIPTION.rst
fastfood-1.1.0.dist-info/entry_points.txt
fastfood-1.1.0.dist-info/METADATA
fastfood-1.1.0.dist-info/metadata.json
fastfood-1.1.0.dist-info/pbr.json
fastfood-1.1.0.dist-info/RECORD
fastfood-1.1.0.dist-info/top_level.txt
fastfood-1.1.0.dist-info/WHEEL
