Metadata-Version: 2.0
Name: fastfood
Version: 1.1.0
Summary: Chef Cookbook Wizardry
Home-page: https://github.com/rackerlabs/fastfood
Author: Rackers
Author-email: samuel.stavinoha@rackspace.com
License: Apache License, Version 2.0
Keywords: chef cookbook templating generation
Platform: UNKNOWN
Classifier: Intended Audience :: Developers
Classifier: License :: OSI Approved :: Apache Software License
Classifier: Operating System :: OS Independent
Classifier: Topic :: Software Development
Classifier: Topic :: Software Development :: Code Generators
Classifier: Development Status :: 4 - Beta
Classifier: Programming Language :: Python
Classifier: Programming Language :: Python :: 2
Classifier: Programming Language :: Python :: 2.7
Classifier: Programming Language :: Python :: 3
Classifier: Programming Language :: Python :: 3.4
Requires-Dist: Jinja2 (==2.7.3)
